aioftps3.py
aioftps3-0.0.6.dist-info/LICENSE
aioftps3-0.0.6.dist-info/METADATA
aioftps3-0.0.6.dist-info/WHEEL
aioftps3-0.0.6.dist-info/top_level.txt
aioftps3-0.0.6.dist-info/RECORD
