Metadata-Version: 2.1
Name: aioftps3
Version: 0.0.6
Summary: FTP in front of AWS S3, powered by asyncio and aiohttp
Home-page: https://github.com/uktrade/aioftps3
Author: Department for International Trade - WebOps
Author-email: webops@digital.trade.gov.uk
License: UNKNOWN
Platform: UNKNOWN
Classifier: Programming Language :: Python :: 3
Classifier: License :: OSI Approved :: MIT License
Classifier: Operating System :: OS Independent
Classifier: Framework :: AsyncIO
Classifier: Topic :: Internet :: File Transfer Protocol (FTP)
Requires-Dist: aiohttp
